CONTRIBUTING.md
LICENSE
MANIFEST.in
README.md
requirements.txt
setup.py
conan_guide.egg-info/PKG-INFO
conan_guide.egg-info/SOURCES.txt
conan_guide.egg-info/dependency_links.txt
conan_guide.egg-info/entry_points.txt
conan_guide.egg-info/requires.txt
conan_guide.egg-info/top_level.txt
conanguide/__init__.py
conanguide/app.py
conanguide/info.py
conanguide/api/__init__.py
conanguide/api/conan_api.py
conanguide/client/__init__.py
conanguide/client/runner/__init__.py
conanguide/client/runner/command_runner.py
conanguide/data/__init__.py
conanguide/data/conan_profile.py
conanguide/data/conan_recipe.py
conanguide/data/conan_remote.py
conanguide/ui/__init__.py
conanguide/ui/config/__init__.py
conanguide/ui/config/ui_config.py
conanguide/ui/controller/__init__.py
conanguide/ui/controller/tab/__init__.py
conanguide/ui/controller/tab/cache/__init__.py
conanguide/ui/controller/tab/cache/conan_package.py
conanguide/ui/controller/tab/cache/conan_package_inspect.py
conanguide/ui/controller/tab/cache/conan_recipe.py
conanguide/ui/controller/tab/cache/conan_recipe_inspect.py
conanguide/ui/controller/tab/cache/directory_tree.py
conanguide/ui/controller/tab/profile/__init__.py
conanguide/ui/controller/tab/profile/conan_profile.py
conanguide/ui/controller/tab/remote/__init__.py
conanguide/ui/controller/tab/remote/conan_remote.py
conanguide/ui/controller/tab/remote/conan_remote_reference.py
conanguide/ui/dialog/__init__.py
conanguide/ui/dialog/about/__init__.py
conanguide/ui/dialog/about/about.py
conanguide/ui/dialog/about/about_ui.py
conanguide/ui/dialog/edit/__init__.py
conanguide/ui/dialog/edit/name/__init__.py
conanguide/ui/dialog/edit/name/edit_name.py
conanguide/ui/dialog/edit/name/edit_name_ui.py
conanguide/ui/dialog/edit/remote/__init__.py
conanguide/ui/dialog/edit/remote/edit_remote.py
conanguide/ui/dialog/edit/remote/edit_remote_ui.py
conanguide/ui/main/__init__.py
conanguide/ui/main/main_window.py
conanguide/ui/main/main_window_ui.py
conanguide/ui/res/__init__.py
conanguide/ui/res/resources_rc.py
conanguide/ui/widget/__init__.py
conanguide/ui/widget/profile/__init__.py
conanguide/ui/widget/profile/profile_attribute.py
conanguide/ui/widget/profile/profile_attribute_ui.py
