Metadata-Version: 2.1
Name: conan-guide
Version: 1.2.0
Summary: Qt based Graphical User Interface (GUI) to interact with local cache of conan package manager
Home-page: https://github.com/afri-bit/conan-guide
Author: Afrizal Herlambang
Author-email: afri.bit@outlook.com
License: MIT
Keywords: conan,conan.io,GUI,Conan GUI,PySide2
Platform: UNKNOWN
Classifier: License :: OSI Approved :: MIT License
Classifier: Intended Audience :: Developers
Classifier: Programming Language :: Python :: 3
Classifier: Programming Language :: Python :: 3.6
Classifier: Programming Language :: Python :: 3.7
Classifier: Programming Language :: Python :: 3.8
Classifier: Environment :: X11 Applications :: Qt
Classifier: Environment :: Win32 (MS Windows)
Classifier: Operating System :: Microsoft :: Windows :: Windows 10
Classifier: Operating System :: POSIX :: Linux
